pysynthbio/__init__.py
pysynthbio/call_model_api.py
pysynthbio/get_example_query.py
pysynthbio/key_handlers.py
pysynthbio/list_models.py
pysynthbio/output_transformers.py
pysynthbio-4.0.5.dist-info/licenses/LICENSE
pysynthbio-4.0.5.dist-info/METADATA
pysynthbio-4.0.5.dist-info/WHEEL
pysynthbio-4.0.5.dist-info/top_level.txt
pysynthbio-4.0.5.dist-info/RECORD
