Metadata-Version: 2.4
Name: pysynthbio
Version: 4.0.5
Summary: A package to retrieve data and models from Synthesize Bio's API
Author: Alex David, Candace Savonen
License-Expression: MIT
Project-URL: Homepage, https://github.com/synthesizebio/pysynthbio
Project-URL: Issues, https://github.com/synthesizebio/pysynthbio/issues
License-File: LICENSE
Requires-Dist: numpy>=2.2.5
Requires-Dist: pandas>=2.2.3
Requires-Dist: requests
Requires-Dist: keyring>=23.0.0
Provides-Extra: secure
Requires-Dist: keyring>=23.0.0; extra == "secure"
Provides-Extra: all
Requires-Dist: keyring>=23.0.0; extra == "all"
Provides-Extra: dev
Requires-Dist: pytest>=7.0.0; extra == "dev"
Requires-Dist: pytest-cov>=4.0.0; extra == "dev"
Requires-Dist: ruff; extra == "dev"
Requires-Dist: mypy; extra == "dev"
Requires-Dist: black; extra == "dev"
Requires-Dist: build; extra == "dev"
Provides-Extra: docs
Requires-Dist: sphinx; extra == "docs"
Requires-Dist: sphinx-autobuild; extra == "docs"
Dynamic: license-file
